schwarm/__init__.py
schwarm/app.py
schwarm/index.html
schwarm/assets/index-BA1OFJnw.css
schwarm/assets/index-CYUXeYus.js
schwarm/configs/__init__.py
schwarm/configs/telemetry_config.py
schwarm/configs/base/__init__.py
schwarm/configs/base/base_config.py
schwarm/core/__init__.py
schwarm/core/logging.py
schwarm/core/schwarm.py
schwarm/core/stream.py
schwarm/core/tools.py
schwarm/events/__init__.py
schwarm/events/event.py
schwarm/manager/stream_manager.py
schwarm/models/__init__.py
schwarm/models/agent.py
schwarm/models/event.py
schwarm/models/message.py
schwarm/models/provider_context.py
schwarm/models/result.py
schwarm/models/types.py
schwarm/models/agents/fan_out_agent.py
schwarm/models/agents/handoff_agent.py
schwarm/models/agents/terminator.py
schwarm/models/agents/user_agent.py
schwarm/protocols/agent_protocol.py
schwarm/provider/__init__.py
schwarm/provider/information_provider.py
schwarm/provider/llm_provider.py
schwarm/provider/mongo_db_provider.py
schwarm/provider/provider_manager.py
schwarm/provider/provider_presets.py
schwarm/provider/user_interaction_provider.py
schwarm/provider/zep_provider.py
schwarm/provider/base/__init__.py
schwarm/provider/base/base_event_handle_provider.py
schwarm/provider/base/base_llm_provider.py
schwarm/provider/base/base_provider.py
schwarm/telemetry/__init__.py
schwarm/telemetry/file_telemetry_exporter.py
schwarm/telemetry/jaeger_span_exporter.py
schwarm/telemetry/socketio_manager.py
schwarm/telemetry/sqlite_telemetry_exporter.py
schwarm/telemetry/telemetry_manager.py
schwarm/telemetry/telemetry_presets.py
schwarm/telemetry/base/__init__.py
schwarm/telemetry/base/http_telemetry_exporter.py
schwarm/telemetry/base/telemetry_exporter.py
schwarm/utils/__init__.py
schwarm/utils/file.py
schwarm/utils/function.py
schwarm/utils/handling.py
schwarm/utils/merge.py
schwarm/utils/settings.py
schwarm-0.1.84.dist-info/METADATA
schwarm-0.1.84.dist-info/WHEEL
schwarm-0.1.84.dist-info/entry_points.txt
schwarm-0.1.84.dist-info/RECORD
