Metadata-Version: 2.4
Name: schwarm
Version: 0.1.84
Summary: A very opinionated package for building agent systems. Also very alpha.
Requires-Python: >=3.12
Requires-Dist: arxiv>=2.1.3
Requires-Dist: beautifulsoup4>=4.12.3
Requires-Dist: devtools>=0.12.2
Requires-Dist: diskcache>=5.6.3
Requires-Dist: fastapi>=0.115.5
Requires-Dist: ipywidgets>=8.1.5
Requires-Dist: litellm>=1.53.1
Requires-Dist: litestar>=2.13.0
Requires-Dist: loguru>=0.7.2
Requires-Dist: nest-asyncio>=1.6.0
Requires-Dist: opentelemetry-api>=1.28.2
Requires-Dist: opentelemetry-exporter-jaeger>=1.21.0
Requires-Dist: opentelemetry-exporter-otlp>=1.28.2
Requires-Dist: opentelemetry-instrumentation-logging>=0.49b2
Requires-Dist: opentelemetry-sdk>=1.28.2
Requires-Dist: orjson>=3.10.11
Requires-Dist: poethepoet>=0.29.0
Requires-Dist: pydantic>=2.9.2
Requires-Dist: pymongo>=4.10.1
Requires-Dist: python-decouple>=3.8
Requires-Dist: python-dotenv>=1.0.1
Requires-Dist: python-socketio[async]>=5.11.4
Requires-Dist: pywebview>=5.3.2
Requires-Dist: rich>=13.9.4
Requires-Dist: tavily-python>=0.5.0
Requires-Dist: typer>=0.12.5
Requires-Dist: uvicorn>=0.32.1
Requires-Dist: websockets>=14.1
Requires-Dist: zep-python>=2.0.2
